hex_mcp/__init__.py
hex_mcp/config.py
hex_mcp/server.py
hex_mcp-0.1.10.dist-info/METADATA
hex_mcp-0.1.10.dist-info/WHEEL
hex_mcp-0.1.10.dist-info/entry_points.txt
hex_mcp-0.1.10.dist-info/RECORD
