Metadata-Version: 2.4
Name: hex-mcp
Version: 0.1.10
Summary: A MCP server for Hex
Author-email: Franccesco Orozco <franccesco@codingdose.info>
Requires-Python: >=3.12
Requires-Dist: backoff>=2.2.1
Requires-Dist: httpx>=0.27.0
Requires-Dist: mcp>=1.3.0
Requires-Dist: python-dotenv>=1.0.1
Requires-Dist: pyyaml>=6.0.2
Requires-Dist: typer>=0.15.2
Provides-Extra: dev
Requires-Dist: mcp[cli]>=1.3.0; extra == 'dev'
